winrt/_winrt_windows_ui_webui.cp39-win_amd64.pyd
winrt/_winrt_windows_ui_webui.pyi
winrt/windows/ui/webui/__init__.py
winrt/windows/ui/webui/py.typed
winrt_windows_ui_webui-3.2.1.dist-info/METADATA
winrt_windows_ui_webui-3.2.1.dist-info/WHEEL
winrt_windows_ui_webui-3.2.1.dist-info/top_level.txt
winrt_windows_ui_webui-3.2.1.dist-info/RECORD
