Metadata-Version: 2.4
Name: winrt-Windows.UI.WebUI
Version: 3.2.1
Summary: Python projection of Windows Runtime (WinRT) APIs
License-Expression: MIT
Project-URL: Documentation, https://pywinrt.readthedocs.io
Project-URL: Repository, https://github.com/pywinrt/pywinrt
Project-URL: Changelog, https://github.com/pywinrt/pywinrt/blob/main/CHANGELOG.md
Classifier: Operating System :: Microsoft :: Windows
Classifier: Programming Language :: Python :: 3
Classifier: Programming Language :: Python :: Implementation :: CPython
Classifier: Intended Audience :: Developers
Requires-Python: >=3.9
Requires-Dist: winrt-runtime~=3.2.1.0
Provides-Extra: all
Requires-Dist: winrt-Windows.ApplicationModel[all]~=3.2.1.0; extra == "all"
Requires-Dist: winrt-Windows.ApplicationModel.Activation[all]~=3.2.1.0; extra == "all"
Requires-Dist: winrt-Windows.ApplicationModel.Appointments.AppointmentsProvider[all]~=3.2.1.0; extra == "all"
Requires-Dist: winrt-Windows.ApplicationModel.Background[all]~=3.2.1.0; extra == "all"
Requires-Dist: winrt-Windows.ApplicationModel.Calls[all]~=3.2.1.0; extra == "all"
Requires-Dist: winrt-Windows.ApplicationModel.Contacts[all]~=3.2.1.0; extra == "all"
Requires-Dist: winrt-Windows.ApplicationModel.Contacts.Provider[all]~=3.2.1.0; extra == "all"
Requires-Dist: winrt-Windows.ApplicationModel.Core[all]~=3.2.1.0; extra == "all"
Requires-Dist: winrt-Windows.ApplicationModel.DataTransfer[all]~=3.2.1.0; extra == "all"
Requires-Dist: winrt-Windows.ApplicationModel.DataTransfer.ShareTarget[all]~=3.2.1.0; extra == "all"
Requires-Dist: winrt-Windows.ApplicationModel.Search[all]~=3.2.1.0; extra == "all"
Requires-Dist: winrt-Windows.ApplicationModel.UserDataAccounts.Provider[all]~=3.2.1.0; extra == "all"
Requires-Dist: winrt-Windows.ApplicationModel.Wallet[all]~=3.2.1.0; extra == "all"
Requires-Dist: winrt-Windows.Devices.Enumeration[all]~=3.2.1.0; extra == "all"
Requires-Dist: winrt-Windows.Devices.Printers.Extensions[all]~=3.2.1.0; extra == "all"
Requires-Dist: winrt-Windows.Foundation[all]~=3.2.1.0; extra == "all"
Requires-Dist: winrt-Windows.Foundation.Collections[all]~=3.2.1.0; extra == "all"
Requires-Dist: winrt-Windows.Media.SpeechRecognition[all]~=3.2.1.0; extra == "all"
Requires-Dist: winrt-Windows.Security.Authentication.Web[all]~=3.2.1.0; extra == "all"
Requires-Dist: winrt-Windows.Security.Authentication.Web.Provider[all]~=3.2.1.0; extra == "all"
Requires-Dist: winrt-Windows.Storage[all]~=3.2.1.0; extra == "all"
Requires-Dist: winrt-Windows.Storage.Pickers.Provider[all]~=3.2.1.0; extra == "all"
Requires-Dist: winrt-Windows.Storage.Provider[all]~=3.2.1.0; extra == "all"
Requires-Dist: winrt-Windows.Storage.Search[all]~=3.2.1.0; extra == "all"
Requires-Dist: winrt-Windows.Storage.Streams[all]~=3.2.1.0; extra == "all"
Requires-Dist: winrt-Windows.System[all]~=3.2.1.0; extra == "all"
Requires-Dist: winrt-Windows.UI[all]~=3.2.1.0; extra == "all"
Requires-Dist: winrt-Windows.Web[all]~=3.2.1.0; extra == "all"
Requires-Dist: winrt-Windows.Web.Http[all]~=3.2.1.0; extra == "all"
Requires-Dist: winrt-Windows.Web.UI[all]~=3.2.1.0; extra == "all"
